Metadata-Version: 2.1
Name: cloudbatch
Version: 0.2
Summary: Python objects for simplifying batch analysis of data on google buckets
Home-page: https://github.com/davbyr/cloudbatch
Download-URL: https://github.com/davbyr/cloudbatch/archive/refs/tags/v0.2.tar.gz
Author: David Byrne
License: MIT
Platform: UNKNOWN
Classifier: Development Status :: 3 - Alpha
Classifier: Intended Audience :: Developers
Classifier: License :: OSI Approved :: MIT License
Classifier: Operating System :: OS Independent
Classifier: Programming Language :: Python
Classifier: Programming Language :: Python :: 3.7
Classifier: Programming Language :: Python :: 3.8
Classifier: Topic :: Software Development :: Libraries :: Python Modules
Requires-Python: >=3.7
License-File: LICENSE.txt
